pyceptive/__init__.py
pyceptive/_version.py
pyceptive/pyceptive.py
pyceptive-0.0.1.dist-info/LICENSE
pyceptive-0.0.1.dist-info/METADATA
pyceptive-0.0.1.dist-info/WHEEL
pyceptive-0.0.1.dist-info/top_level.txt
pyceptive-0.0.1.dist-info/RECORD
